{
    "command": {
        "color": "GREEN",
        "statistic": "See: <http://leaderboard.ccns.ncku.edu.tw>",
        "help": {
            "title": "help",
            "description": "This is quiz chat bot escho! Answer question by clicking any alphabet emoji below the question.\n\nAll commands start with `/`. To use the commands in a group channel, add the prefix `@escho#1145` to the command. For example, you can show your status to others in **qa-quiz** by sending `@escho#1145 /status` in the qa-quiz channel.",
            "fields": [
                {
                    "name": "/help",
                    "value": "Show this help message"
                },
                {
                    "name": "/start",
                    "value": "Register by your discord id and start QA quiz in a private channel. The bot will then send you your status. You should check whether the status is yours, and then you can register a new one by specifying the new id with `/start your-new-id` (the following command)."
                },
                {
                    "name": "/next",
                    "value": "Ask for the next question. The previous question will still show up in the future."
                },
                {
                    "name": "/status",
                    "value": "Show your quiz status"
                },
                {
                    "name": "/statistic",
                    "value": "Show all users' status"
                }
            ]
        }
    },
    "emoji": {
        "right": "👍",
        "wrong": "👎",
        "number": ["🇦", "🇧", "🇨", "🇩"]
    },
    "right": [
        "777! 聊天室 7 起來!",
        "すごーい! (sugoi)",
        "たーのしー！(tanoshii)",
        "教授：答的不錯，晚上到實驗室找我",
        "不錯嘛，這個屌",
        "答對囉",
        "超過 100 分",
        "完全的正確",
        "睿智的人類，去支配世界吧！",
        "渾身充滿了勝利的氣息…！",
        "這回答我只能給 82 分，剩餘的分數拆成 666 送給你",
        "87 分，不能再高了",
        "你資工系？",
        "嗯嗯，跟我想的一樣",
        "真沒想到你可以到四樓來呢，不過就到這裡為止了！接下來就由我鎖鏈的康妮來做你的對手！",
        "到此為止了年輕人，就算你打敗了鎖鍊的康妮，也不會是我狂爆微笑殺手奧特斯的對手的！",
        "其實……，我是四大王裡最弱的，不要太得意了……",
        "哈哈😂😂😂👍👍這你自己想出來的嗎😳😳很厲害欸😎😎skrskr🤙🤙🤙",
        "轟隆隆隆🤣🤣隆隆隆隆衝衝衝衝😏😏😏拉風😎😎😎引擎發動🔑🔑🔑引擎發動+🚗+👉+🚗",
        "想不到…檳友…也是……略懂…略…懂…",
        "誰一拜？咖嘎壓哭！！",
        "奇怪的知識增加了!!!",
        "⁶⁶⁶⁶⁶ ⁶⁶66６６６⁶⁶⁶⁶⁶ ₆₆₆₆可以啊.这波 ₆₆₆₆⁶⁶⁶⁶⁶⁶卧槽 ⁶⁶666",
        "下面這題再答對，主委加 2000 我自己再加碼到 5000 大給供賀毋賀啊？",
        "巨槌瑞斯一打五～還敢下來啊冰鳥！",
        "答對這題，我心中卻沒有一絲一毫的喜悅",
        "真相永遠只有一個 👇👓🎀🔍",
        "謝謝超負荷讓我知道",
        "同意啦哪次不同意",
        "看來你很閒呢, 那就加入 CCNS 吧(?",
        "你贏惹 ob'_'ov",
        "不如來跟我們一起出題?",
        "Wonderful Day",
        "大腦在星爆…",
        "這題就當作送分啦!",
        "你是不是偷看過我們的 database?"
    ],
    "wrong": [
        "連這題不會，你只能去寫 COBOL 了",
        "這也錯？連 PHP 工程師都答的比你好",
        "答錯了啦，是不會查 stackoverflow 嗎？",
        "Error. STFW, OK?",
        "嘿嘿，見鬼啦，不是這個吧。",
        "答錯 0 分",
        "拜託，幫我撐十秒。",
        "會有更多題目讓你答錯的，不用擔心",
        "老師上課有沒有在聽？",
        "雖然很可惜，但也不用太擔心",
        "你這輩子就這樣了",
        "崩╰(〒皿〒)╯潰",
        "無駄無駄無駄無駄無駄無駄無駄！！！",
        "叭叭",
        "script kid?",
        "りしれ供さ小",
        "噓 ccns: ?",
        "支離滅裂な思考発言",
        "當我塑膠？",
        "我就爛 👍👍👍",
        "檳友…還…菁多……加…油…",
        "我就怕被罵阿",
        "這題不會只能去文組了",
        "??¿¿??？？？⁉❓❓",
        "是在哈囉？",
        "好，我們繼續送幸福",
        "每場都這樣盡量戳盡量戳操我在這裡誠摯呼籲啊你凡事被我有戳到被我記下來的",
        "AD 在幹三小啊？故意的是不是啊？",
        "像極了愛情",
        "咩噗😭",
        "fuck you nvidia",
        "press F to pay respects",
        "我跟你談大海，你跟我談浴缸？",
        "太…太大意惹！",
        "我不直接回答你，我用栗子回答你",
        "啊哈哈，佐祐理不清楚",
        "你為什麼不問問神奇海螺呢？",
        "每一題都答錯，你也不簡單啊…",
        "你絕對是故意的吧?對吧?對吧?",
        "這是只存在我們倆中間的秘密喔！",
        "這並不是結束, 而是嶄新的開始",
        "你踩到陷阱，損失了 1 點生命值",
        "系統管理員使用了影分身，你的命中率降低了"
    ]
}

